rsplitter-0.2.1.dist-info/METADATA
rsplitter-0.2.1.dist-info/WHEEL
rsplitter/__init__.py
rsplitter/rsplitter.pyd
rsplitter-0.2.1.dist-info/RECORD
