Metadata-Version: 2.1
Name: rsplitter
Version: 0.2.1
Classifier: Programming Language :: Rust
Classifier: Programming Language :: Python :: Implementation :: CPython
Classifier: Programming Language :: Python :: Implementation :: PyPy
Summary: Rust implementation of a words splitter
Author-email: Omar MHAIMDAT <omarmhaidmat@gmail.com>
Requires-Python: >=3.7
